pruvi
