Metadata-Version: 1.0
Name: pruvi
Version: 0.3.0
Summary: Python3.6+ package to create proofs for certain parts of different types of documents using Merkle Trees.
Home-page: https://github.com/febrezo/pruvi
Author: Félix Brezo (@febrezo)
Author-email: UNKNOWN
License: GNU GPLv3+
Platform: UNKNOWN
